{
    "1": {
        "function": "faceShow",
        "char": "Rafael",
        "pos": 0
    },
    "2": {
        "function": "dialogueShow",
        "pos": 0,
        "text": ["Hi, my name",
                "is Rafael"]
    },
    "3": {
        "function": "say",
        "text": ["How are you?"]
    },
    "4": {
        "function": "dialogueShow",
        "pos": 0,
        "text": ["I'm fine, thanks",
                 "And you?"]
    },
    "5": {
        "function": "choose",
        "text": "Choose an answer:",
        "opts": ["Fine too", "Go to hell", ""],
        "goto": ["6", "9", ""]
    },
    "6": {
        "function": "dialogueShow",
        "pos": 0,
        "text": ["Top"]
    },
    "7": {
        "function": "faceHide",
        "char": "Rafael",
        "pos": 0
    },
    "8": {
        "function": "End"
    },
    "9": {
        "function": "dialogueShow",
        "pos": 0,
        "text": ["How rude!!!"]
    },
    "10": {
        "function": "faceHide",
        "char": "Rafael",
        "pos": 0
    },
    "11": {
        "function": "End"
    }
}
